Metadata-Version: 1.1
Name: pyairpal
Version: 1.1.1
Summary: Python Client/SDK for Airpal
Home-page: https://github.com/ebob9/pyairpal
Author: Aaron Edwards
Author-email: pyairpal@ebob9.com
License: MIT
Platform: UNKNOWN
Classifier: Development Status :: 5 - Production/Stable
Classifier: Intended Audience :: Developers
Classifier: License :: OSI Approved :: MIT License
Classifier: Programming Language :: Python :: 2.7
Classifier: Programming Language :: Python :: 3
